pollingstream/__init__.py
pollingstream/client.py
pollingstream/server.py
pollingstream-0.1.1.dist-info/METADATA
pollingstream-0.1.1.dist-info/WHEEL
pollingstream-0.1.1.dist-info/RECORD
