Metadata-Version: 2.1
Name: pollingstream
Version: 0.1.1
Summary: A polling-based websocket alternative (used for applications where only polling can be used).
Author: BadPythonCoder
Author-email: no@email.foru
Requires-Python: >=3.7,<4.0
Classifier: Programming Language :: Python :: 3
Classifier: Programming Language :: Python :: 3.7
Classifier: Programming Language :: Python :: 3.8
Classifier: Programming Language :: Python :: 3.9
Classifier: Programming Language :: Python :: 3.10
Classifier: Programming Language :: Python :: 3.11
Requires-Dist: requests (>=2.28.2,<3.0.0)
